{
  "project_info": {
    "project_number": "960754275384",
    "firebase_url": "https://t1reporter-default-rtdb.europe-west1.firebasedatabase.app",
    "project_id": "t1reporter",
    "storage_bucket": "t1reporter.appspot.com"
  },
  "client": [
    {
      "client_info": {
        "mobilesdk_app_id": "1:960754275384:android:6e7eca2072ebe88a7842cd",
        "android_client_info": {
          "package_name": "com.example.t1digitalreporter"
        }
      },
      "oauth_client": [
        {
          "client_id": "960754275384-b54h3invs4bgojtlmkoh0o7iqjgtogqn.apps.googleusercontent.com",
          "client_type": 1,
          "android_info": {
            "package_name": "com.example.t1digitalreporter",
            "certificate_hash": "630f99198446c30d0a529ee0ba78dd83c7fef83a"
          }
        },
        {
          "client_id": "960754275384-vanps4ck5u5jdccihh3pn9aobjk5lsnu.apps.googleusercontent.com",
          "client_type": 3
        }
      ],
      "api_key": [
        {
          "current_key": "AIzaSyCHgnOBlv4G0VtwkG8ymWT-BYf_KGOs6UM"
        }
      ],
      "services": {
        "appinvite_service": {
          "other_platform_oauth_client": [
            {
              "client_id": "960754275384-vanps4ck5u5jdccihh3pn9aobjk5lsnu.apps.googleusercontent.com",
              "client_type": 3
            }
          ]
        }
      }
    }
  ],
  "configuration_version": "1"
}